rossetta_flask.py
rossetta_flask-0.1.0.dist-info/licenses/LICENSE
rossetta_flask-0.1.0.dist-info/METADATA
rossetta_flask-0.1.0.dist-info/WHEEL
rossetta_flask-0.1.0.dist-info/top_level.txt
rossetta_flask-0.1.0.dist-info/RECORD
