Metadata-Version: 2.4
Name: rossetta-flask
Version: 0.1.0
Summary: Zero-config network request obfuscation middleware for Flask - protect your APIs from reverse engineering
Home-page: https://github.com/yiheinchai/rossetta-api
Author: Rossetta API Team
Author-email: 
License: MIT
Project-URL: Bug Tracker, https://github.com/yiheinchai/rossetta-api/issues
Project-URL: Documentation, https://github.com/yiheinchai/rossetta-api#readme
Project-URL: Source Code, https://github.com/yiheinchai/rossetta-api/tree/main/packages/rossetta-flask
Keywords: flask middleware encryption obfuscation security rossetta api-security aes-256 hmac endpoint-obfuscation
Classifier: Development Status :: 4 - Beta
Classifier: Intended Audience :: Developers
Classifier: License :: OSI Approved :: MIT License
Classifier: Programming Language :: Python :: 3
Classifier: Programming Language :: Python :: 3.8
Classifier: Programming Language :: Python :: 3.9
Classifier: Programming Language :: Python :: 3.10
Classifier: Programming Language :: Python :: 3.11
Classifier: Programming Language :: Python :: 3.12
Classifier: Framework :: Flask
Classifier: Topic :: Internet :: WWW/HTTP
Classifier: Topic :: Security :: Cryptography
Classifier: Topic :: Software Development :: Libraries :: Python Modules
Requires-Python: >=3.8
License-File: LICENSE
Requires-Dist: flask>=2.3.2
Requires-Dist: cryptography>=42.0.4
Dynamic: author
Dynamic: classifier
Dynamic: description
Dynamic: description-content-type
Dynamic: home-page
Dynamic: keywords
Dynamic: license
Dynamic: license-file
Dynamic: project-url
Dynamic: requires-dist
Dynamic: requires-python
Dynamic: summary
